filedown/__init__.py
filedown/concurrent_download.py
filedown/filedown.py
filedown-0.6.2.dist-info/LICENSE
filedown-0.6.2.dist-info/METADATA
filedown-0.6.2.dist-info/WHEEL
filedown-0.6.2.dist-info/entry_points.txt
filedown-0.6.2.dist-info/top_level.txt
filedown-0.6.2.dist-info/RECORD
