Metadata-Version: 2.1
Name: filedown
Version: 0.6.2
Summary: filedown: Multi Thread Downloader
Home-page: https://github.com/windard/filedown
Author: Windard Yang
Author-email: windard@qq.com
License: MIT
Platform: UNKNOWN
Classifier: Programming Language :: Python :: 2.7
Classifier: Programming Language :: Python :: 3.6
Classifier: Programming Language :: Python :: 3.7
Classifier: License :: OSI Approved :: MIT License
Classifier: Operating System :: OS Independent
Requires-Dist: Click
Requires-Dist: tqdm
Requires-Dist: requests
